greetings/hello.py
greetings/world.py
greetings/__init__.py
HelloTestPackage-3.0.0.dist-info/DESCRIPTION.rst
HelloTestPackage-3.0.0.dist-info/METADATA
HelloTestPackage-3.0.0.dist-info/metadata.json
HelloTestPackage-3.0.0.dist-info/RECORD
HelloTestPackage-3.0.0.dist-info/top_level.txt
HelloTestPackage-3.0.0.dist-info/WHEEL
